{
    "data": [
        {
            "ts": 1523595600,
            "count": 0
        },
        {
            "ts": 1523596800,
            "count": 0
        },
        {
            "ts": 1523598000,
            "count": 0
        },
        {
            "ts": 1523599200,
            "count": 0
        },
        {
            "ts": 1523600400,
            "count": 0
        },
        {
            "ts": 1523601600,
            "count": 0
        },
        {
            "ts": 1523602800,
            "count": 0
        },
        {
            "ts": 1523604000,
            "count": 1
        },
        {
            "ts": 1523605200,
            "count": 0
        },
        {
            "ts": 1523606400,
            "count": 0
        },
        {
            "ts": 1523607600,
            "count": 0
        },
        {
            "ts": 1523608800,
            "count": 0
        },
        {
            "ts": 1523610000,
            "count": 0
        },
        {
            "ts": 1523611200,
            "count": 0
        },
        {
            "ts": 1523612400,
            "count": 0
        },
        {
            "ts": 1523613600,
            "count": 0
        },
        {
            "ts": 1523614800,
            "count": 0
        },
        {
            "ts": 1523616000,
            "count": 0
        },
        {
            "ts": 1523617200,
            "count": 0
        },
        {
            "ts": 1523618400,
            "count": 0
        },
        {
            "ts": 1523619600,
            "count": 0
        },
        {
            "ts": 1523620800,
            "count": 0
        },
        {
            "ts": 1523622000,
            "count": 0
        },
        {
            "ts": 1523623200,
            "count": 0
        },
        {
            "ts": 1523624400,
            "count": 0
        },
        {
            "ts": 1523625600,
            "count": 0
        },
        {
            "ts": 1523626800,
            "count": 0
        },
        {
            "ts": 1523628000,
            "count": 0
        },
        {
            "ts": 1523629200,
            "count": 0
        },
        {
            "ts": 1523630400,
            "count": 0
        },
        {
            "ts": 1523631600,
            "count": 0
        },
        {
            "ts": 1523632800,
            "count": 0
        },
        {
            "ts": 1523634000,
            "count": 0
        },
        {
            "ts": 1523635200,
            "count": 0
        },
        {
            "ts": 1523636400,
            "count": 0
        },
        {
            "ts": 1523637600,
            "count": 0
        },
        {
            "ts": 1523638800,
            "count": 0
        },
        {
            "ts": 1523640000,
            "count": 0
        },
        {
            "ts": 1523641200,
            "count": 0
        },
        {
            "ts": 1523642400,
            "count": 0
        },
        {
            "ts": 1523643600,
            "count": 0
        },
        {
            "ts": 1523644800,
            "count": 0
        },
        {
            "ts": 1523646000,
            "count": 0
        },
        {
            "ts": 1523647200,
            "count": 0
        },
        {
            "ts": 1523648400,
            "count": 0
        },
        {
            "ts": 1523649600,
            "count": 0
        },
        {
            "ts": 1523650800,
            "count": 0
        },
        {
            "ts": 1523652000,
            "count": 0
        },
        {
            "ts": 1523653200,
            "count": 0
        },
        {
            "ts": 1523654400,
            "count": 0
        },
        {
            "ts": 1523655600,
            "count": 0
        },
        {
            "ts": 1523656800,
            "count": 0
        },
        {
            "ts": 1523658000,
            "count": 0
        },
        {
            "ts": 1523659200,
            "count": 0
        },
        {
            "ts": 1523660400,
            "count": 0
        },
        {
            "ts": 1523661600,
            "count": 0
        },
        {
            "ts": 1523662800,
            "count": 0
        },
        {
            "ts": 1523664000,
            "count": 0
        },
        {
            "ts": 1523665200,
            "count": 0
        },
        {
            "ts": 1523666400,
            "count": 0
        },
        {
            "ts": 1523667600,
            "count": 0
        },
        {
            "ts": 1523668800,
            "count": 0
        },
        {
            "ts": 1523670000,
            "count": 0
        },
        {
            "ts": 1523671200,
            "count": 0
        },
        {
            "ts": 1523672400,
            "count": 0
        },
        {
            "ts": 1523673600,
            "count": 0
        },
        {
            "ts": 1523674800,
            "count": 0
        },
        {
            "ts": 1523676000,
            "count": 0
        },
        {
            "ts": 1523677200,
            "count": 0
        },
        {
            "ts": 1523678400,
            "count": 0
        },
        {
            "ts": 1523679600,
            "count": 0
        },
        {
            "ts": 1523680800,
            "count": 0
        }
    ],
    "meta": {}
}