{
    "data": [
        {
            "ts": 1570251600,
            "count": 0
        },
        {
            "ts": 1570252800,
            "count": 0
        },
        {
            "ts": 1570254000,
            "count": 0
        },
        {
            "ts": 1570255200,
            "count": 0
        },
        {
            "ts": 1570256400,
            "count": 0
        },
        {
            "ts": 1570257600,
            "count": 0
        },
        {
            "ts": 1570258800,
            "count": 0
        },
        {
            "ts": 1570260000,
            "count": 0
        },
        {
            "ts": 1570261200,
            "count": 0
        },
        {
            "ts": 1570262400,
            "count": 0
        },
        {
            "ts": 1570263600,
            "count": 0
        },
        {
            "ts": 1570264800,
            "count": 0
        },
        {
            "ts": 1570266000,
            "count": 0
        },
        {
            "ts": 1570267200,
            "count": 0
        },
        {
            "ts": 1570268400,
            "count": 0
        },
        {
            "ts": 1570269600,
            "count": 0
        },
        {
            "ts": 1570270800,
            "count": 0
        },
        {
            "ts": 1570272000,
            "count": 0
        },
        {
            "ts": 1570273200,
            "count": 0
        },
        {
            "ts": 1570274400,
            "count": 0
        },
        {
            "ts": 1570275600,
            "count": 0
        },
        {
            "ts": 1570276800,
            "count": 0
        },
        {
            "ts": 1570278000,
            "count": 0
        },
        {
            "ts": 1570279200,
            "count": 0
        },
        {
            "ts": 1570280400,
            "count": 0
        },
        {
            "ts": 1570281600,
            "count": 0
        },
        {
            "ts": 1570282800,
            "count": 1
        },
        {
            "ts": 1570284000,
            "count": 0
        },
        {
            "ts": 1570285200,
            "count": 0
        },
        {
            "ts": 1570286400,
            "count": 0
        },
        {
            "ts": 1570287600,
            "count": 0
        },
        {
            "ts": 1570288800,
            "count": 0
        },
        {
            "ts": 1570290000,
            "count": 0
        },
        {
            "ts": 1570291200,
            "count": 0
        },
        {
            "ts": 1570292400,
            "count": 0
        },
        {
            "ts": 1570293600,
            "count": 0
        },
        {
            "ts": 1570294800,
            "count": 0
        },
        {
            "ts": 1570296000,
            "count": 0
        },
        {
            "ts": 1570297200,
            "count": 0
        },
        {
            "ts": 1570298400,
            "count": 0
        },
        {
            "ts": 1570299600,
            "count": 0
        },
        {
            "ts": 1570300800,
            "count": 0
        },
        {
            "ts": 1570302000,
            "count": 0
        },
        {
            "ts": 1570303200,
            "count": 0
        },
        {
            "ts": 1570304400,
            "count": 0
        },
        {
            "ts": 1570305600,
            "count": 1
        },
        {
            "ts": 1570306800,
            "count": 0
        },
        {
            "ts": 1570308000,
            "count": 0
        },
        {
            "ts": 1570309200,
            "count": 0
        },
        {
            "ts": 1570310400,
            "count": 0
        },
        {
            "ts": 1570311600,
            "count": 0
        },
        {
            "ts": 1570312800,
            "count": 0
        },
        {
            "ts": 1570314000,
            "count": 0
        },
        {
            "ts": 1570315200,
            "count": 0
        },
        {
            "ts": 1570316400,
            "count": 0
        },
        {
            "ts": 1570317600,
            "count": 0
        },
        {
            "ts": 1570318800,
            "count": 0
        },
        {
            "ts": 1570320000,
            "count": 0
        },
        {
            "ts": 1570321200,
            "count": 0
        },
        {
            "ts": 1570322400,
            "count": 0
        },
        {
            "ts": 1570323600,
            "count": 0
        },
        {
            "ts": 1570324800,
            "count": 0
        },
        {
            "ts": 1570326000,
            "count": 0
        },
        {
            "ts": 1570327200,
            "count": 0
        },
        {
            "ts": 1570328400,
            "count": 0
        },
        {
            "ts": 1570329600,
            "count": 0
        },
        {
            "ts": 1570330800,
            "count": 0
        },
        {
            "ts": 1570332000,
            "count": 0
        },
        {
            "ts": 1570333200,
            "count": 0
        },
        {
            "ts": 1570334400,
            "count": 0
        },
        {
            "ts": 1570335600,
            "count": 0
        },
        {
            "ts": 1570336800,
            "count": 0
        }
    ],
    "meta": {}
}