{
    "data": [
        {
            "ts": 1518840000,
            "count": 0
        },
        {
            "ts": 1518841200,
            "count": 0
        },
        {
            "ts": 1518842400,
            "count": 0
        },
        {
            "ts": 1518843600,
            "count": 0
        },
        {
            "ts": 1518844800,
            "count": 0
        },
        {
            "ts": 1518846000,
            "count": 0
        },
        {
            "ts": 1518847200,
            "count": 0
        },
        {
            "ts": 1518848400,
            "count": 0
        },
        {
            "ts": 1518849600,
            "count": 0
        },
        {
            "ts": 1518850800,
            "count": 0
        },
        {
            "ts": 1518852000,
            "count": 0
        },
        {
            "ts": 1518853200,
            "count": 0
        },
        {
            "ts": 1518854400,
            "count": 0
        },
        {
            "ts": 1518855600,
            "count": 1
        },
        {
            "ts": 1518856800,
            "count": 0
        },
        {
            "ts": 1518858000,
            "count": 1
        },
        {
            "ts": 1518859200,
            "count": 0
        },
        {
            "ts": 1518860400,
            "count": 0
        },
        {
            "ts": 1518861600,
            "count": 0
        },
        {
            "ts": 1518862800,
            "count": 0
        },
        {
            "ts": 1518864000,
            "count": 0
        },
        {
            "ts": 1518865200,
            "count": 0
        },
        {
            "ts": 1518866400,
            "count": 0
        },
        {
            "ts": 1518867600,
            "count": 0
        },
        {
            "ts": 1518868800,
            "count": 0
        },
        {
            "ts": 1518870000,
            "count": 0
        },
        {
            "ts": 1518871200,
            "count": 0
        },
        {
            "ts": 1518872400,
            "count": 0
        },
        {
            "ts": 1518873600,
            "count": 0
        },
        {
            "ts": 1518874800,
            "count": 0
        },
        {
            "ts": 1518876000,
            "count": 0
        },
        {
            "ts": 1518877200,
            "count": 0
        },
        {
            "ts": 1518878400,
            "count": 0
        },
        {
            "ts": 1518879600,
            "count": 0
        },
        {
            "ts": 1518880800,
            "count": 0
        },
        {
            "ts": 1518882000,
            "count": 0
        },
        {
            "ts": 1518883200,
            "count": 0
        },
        {
            "ts": 1518884400,
            "count": 0
        },
        {
            "ts": 1518885600,
            "count": 0
        },
        {
            "ts": 1518886800,
            "count": 0
        },
        {
            "ts": 1518888000,
            "count": 0
        },
        {
            "ts": 1518889200,
            "count": 0
        },
        {
            "ts": 1518890400,
            "count": 0
        },
        {
            "ts": 1518891600,
            "count": 0
        },
        {
            "ts": 1518892800,
            "count": 0
        },
        {
            "ts": 1518894000,
            "count": 0
        },
        {
            "ts": 1518895200,
            "count": 0
        },
        {
            "ts": 1518896400,
            "count": 0
        },
        {
            "ts": 1518897600,
            "count": 0
        },
        {
            "ts": 1518898800,
            "count": 0
        },
        {
            "ts": 1518900000,
            "count": 0
        },
        {
            "ts": 1518901200,
            "count": 0
        },
        {
            "ts": 1518902400,
            "count": 0
        },
        {
            "ts": 1518903600,
            "count": 0
        },
        {
            "ts": 1518904800,
            "count": 0
        },
        {
            "ts": 1518906000,
            "count": 0
        },
        {
            "ts": 1518907200,
            "count": 0
        },
        {
            "ts": 1518908400,
            "count": 0
        },
        {
            "ts": 1518909600,
            "count": 0
        },
        {
            "ts": 1518910800,
            "count": 0
        },
        {
            "ts": 1518912000,
            "count": 0
        },
        {
            "ts": 1518913200,
            "count": 0
        },
        {
            "ts": 1518914400,
            "count": 0
        },
        {
            "ts": 1518915600,
            "count": 0
        },
        {
            "ts": 1518916800,
            "count": 0
        },
        {
            "ts": 1518918000,
            "count": 0
        },
        {
            "ts": 1518919200,
            "count": 0
        },
        {
            "ts": 1518920400,
            "count": 0
        },
        {
            "ts": 1518921600,
            "count": 0
        },
        {
            "ts": 1518922800,
            "count": 0
        },
        {
            "ts": 1518924000,
            "count": 1
        },
        {
            "ts": 1518925200,
            "count": 0
        }
    ],
    "meta": {}
}