{
    "data": [
        {
            "ts": 1561176000,
            "count": 0
        },
        {
            "ts": 1561177200,
            "count": 0
        },
        {
            "ts": 1561178400,
            "count": 0
        },
        {
            "ts": 1561179600,
            "count": 0
        },
        {
            "ts": 1561180800,
            "count": 0
        },
        {
            "ts": 1561182000,
            "count": 0
        },
        {
            "ts": 1561183200,
            "count": 0
        },
        {
            "ts": 1561184400,
            "count": 0
        },
        {
            "ts": 1561185600,
            "count": 0
        },
        {
            "ts": 1561186800,
            "count": 0
        },
        {
            "ts": 1561188000,
            "count": 0
        },
        {
            "ts": 1561189200,
            "count": 0
        },
        {
            "ts": 1561190400,
            "count": 0
        },
        {
            "ts": 1561191600,
            "count": 0
        },
        {
            "ts": 1561192800,
            "count": 0
        },
        {
            "ts": 1561194000,
            "count": 0
        },
        {
            "ts": 1561195200,
            "count": 0
        },
        {
            "ts": 1561196400,
            "count": 0
        },
        {
            "ts": 1561197600,
            "count": 0
        },
        {
            "ts": 1561198800,
            "count": 0
        },
        {
            "ts": 1561200000,
            "count": 0
        },
        {
            "ts": 1561201200,
            "count": 0
        },
        {
            "ts": 1561202400,
            "count": 0
        },
        {
            "ts": 1561203600,
            "count": 0
        },
        {
            "ts": 1561204800,
            "count": 0
        },
        {
            "ts": 1561206000,
            "count": 0
        },
        {
            "ts": 1561207200,
            "count": 0
        },
        {
            "ts": 1561208400,
            "count": 0
        },
        {
            "ts": 1561209600,
            "count": 0
        },
        {
            "ts": 1561210800,
            "count": 0
        },
        {
            "ts": 1561212000,
            "count": 0
        },
        {
            "ts": 1561213200,
            "count": 0
        },
        {
            "ts": 1561214400,
            "count": 0
        },
        {
            "ts": 1561215600,
            "count": 0
        },
        {
            "ts": 1561216800,
            "count": 0
        },
        {
            "ts": 1561218000,
            "count": 0
        },
        {
            "ts": 1561219200,
            "count": 0
        },
        {
            "ts": 1561220400,
            "count": 0
        },
        {
            "ts": 1561221600,
            "count": 0
        },
        {
            "ts": 1561222800,
            "count": 0
        },
        {
            "ts": 1561224000,
            "count": 0
        },
        {
            "ts": 1561225200,
            "count": 0
        },
        {
            "ts": 1561226400,
            "count": 0
        },
        {
            "ts": 1561227600,
            "count": 0
        },
        {
            "ts": 1561228800,
            "count": 0
        },
        {
            "ts": 1561230000,
            "count": 0
        },
        {
            "ts": 1561231200,
            "count": 0
        },
        {
            "ts": 1561232400,
            "count": 0
        },
        {
            "ts": 1561233600,
            "count": 0
        },
        {
            "ts": 1561234800,
            "count": 0
        },
        {
            "ts": 1561236000,
            "count": 0
        },
        {
            "ts": 1561237200,
            "count": 0
        },
        {
            "ts": 1561238400,
            "count": 0
        },
        {
            "ts": 1561239600,
            "count": 0
        },
        {
            "ts": 1561240800,
            "count": 0
        },
        {
            "ts": 1561242000,
            "count": 0
        },
        {
            "ts": 1561243200,
            "count": 0
        },
        {
            "ts": 1561244400,
            "count": 0
        },
        {
            "ts": 1561245600,
            "count": 0
        },
        {
            "ts": 1561246800,
            "count": 0
        },
        {
            "ts": 1561248000,
            "count": 0
        },
        {
            "ts": 1561249200,
            "count": 0
        },
        {
            "ts": 1561250400,
            "count": 0
        },
        {
            "ts": 1561251600,
            "count": 0
        },
        {
            "ts": 1561252800,
            "count": 0
        },
        {
            "ts": 1561254000,
            "count": 0
        },
        {
            "ts": 1561255200,
            "count": 0
        },
        {
            "ts": 1561256400,
            "count": 0
        },
        {
            "ts": 1561257600,
            "count": 0
        },
        {
            "ts": 1561258800,
            "count": 0
        },
        {
            "ts": 1561260000,
            "count": 0
        },
        {
            "ts": 1561261200,
            "count": 0
        }
    ],
    "meta": {}
}