{
    "data": [
        {
            "ts": 1566014400,
            "count": 0
        },
        {
            "ts": 1566015600,
            "count": 0
        },
        {
            "ts": 1566016800,
            "count": 0
        },
        {
            "ts": 1566018000,
            "count": 0
        },
        {
            "ts": 1566019200,
            "count": 0
        },
        {
            "ts": 1566020400,
            "count": 0
        },
        {
            "ts": 1566021600,
            "count": 0
        },
        {
            "ts": 1566022800,
            "count": 0
        },
        {
            "ts": 1566024000,
            "count": 0
        },
        {
            "ts": 1566025200,
            "count": 0
        },
        {
            "ts": 1566026400,
            "count": 0
        },
        {
            "ts": 1566027600,
            "count": 0
        },
        {
            "ts": 1566028800,
            "count": 0
        },
        {
            "ts": 1566030000,
            "count": 0
        },
        {
            "ts": 1566031200,
            "count": 0
        },
        {
            "ts": 1566032400,
            "count": 0
        },
        {
            "ts": 1566033600,
            "count": 0
        },
        {
            "ts": 1566034800,
            "count": 0
        },
        {
            "ts": 1566036000,
            "count": 0
        },
        {
            "ts": 1566037200,
            "count": 0
        },
        {
            "ts": 1566038400,
            "count": 0
        },
        {
            "ts": 1566039600,
            "count": 0
        },
        {
            "ts": 1566040800,
            "count": 0
        },
        {
            "ts": 1566042000,
            "count": 0
        },
        {
            "ts": 1566043200,
            "count": 0
        },
        {
            "ts": 1566044400,
            "count": 0
        },
        {
            "ts": 1566045600,
            "count": 0
        },
        {
            "ts": 1566046800,
            "count": 0
        },
        {
            "ts": 1566048000,
            "count": 0
        },
        {
            "ts": 1566049200,
            "count": 0
        },
        {
            "ts": 1566050400,
            "count": 0
        },
        {
            "ts": 1566051600,
            "count": 0
        },
        {
            "ts": 1566052800,
            "count": 0
        },
        {
            "ts": 1566054000,
            "count": 0
        },
        {
            "ts": 1566055200,
            "count": 0
        },
        {
            "ts": 1566056400,
            "count": 0
        },
        {
            "ts": 1566057600,
            "count": 0
        },
        {
            "ts": 1566058800,
            "count": 0
        },
        {
            "ts": 1566060000,
            "count": 0
        },
        {
            "ts": 1566061200,
            "count": 0
        },
        {
            "ts": 1566062400,
            "count": 0
        },
        {
            "ts": 1566063600,
            "count": 0
        },
        {
            "ts": 1566064800,
            "count": 0
        },
        {
            "ts": 1566066000,
            "count": 0
        },
        {
            "ts": 1566067200,
            "count": 0
        },
        {
            "ts": 1566068400,
            "count": 0
        },
        {
            "ts": 1566069600,
            "count": 0
        },
        {
            "ts": 1566070800,
            "count": 0
        },
        {
            "ts": 1566072000,
            "count": 0
        },
        {
            "ts": 1566073200,
            "count": 0
        },
        {
            "ts": 1566074400,
            "count": 0
        },
        {
            "ts": 1566075600,
            "count": 0
        },
        {
            "ts": 1566076800,
            "count": 0
        },
        {
            "ts": 1566078000,
            "count": 0
        },
        {
            "ts": 1566079200,
            "count": 0
        },
        {
            "ts": 1566080400,
            "count": 0
        },
        {
            "ts": 1566081600,
            "count": 0
        },
        {
            "ts": 1566082800,
            "count": 0
        },
        {
            "ts": 1566084000,
            "count": 0
        },
        {
            "ts": 1566085200,
            "count": 0
        },
        {
            "ts": 1566086400,
            "count": 0
        },
        {
            "ts": 1566087600,
            "count": 0
        },
        {
            "ts": 1566088800,
            "count": 0
        },
        {
            "ts": 1566090000,
            "count": 0
        },
        {
            "ts": 1566091200,
            "count": 0
        },
        {
            "ts": 1566092400,
            "count": 0
        },
        {
            "ts": 1566093600,
            "count": 0
        },
        {
            "ts": 1566094800,
            "count": 0
        },
        {
            "ts": 1566096000,
            "count": 0
        },
        {
            "ts": 1566097200,
            "count": 0
        },
        {
            "ts": 1566098400,
            "count": 0
        },
        {
            "ts": 1566099600,
            "count": 0
        }
    ],
    "meta": {}
}