{
    "data": [
        {
            "ts": 1538798400,
            "count": 0
        },
        {
            "ts": 1538799600,
            "count": 0
        },
        {
            "ts": 1538800800,
            "count": 0
        },
        {
            "ts": 1538802000,
            "count": 0
        },
        {
            "ts": 1538803200,
            "count": 0
        },
        {
            "ts": 1538804400,
            "count": 0
        },
        {
            "ts": 1538805600,
            "count": 0
        },
        {
            "ts": 1538806800,
            "count": 0
        },
        {
            "ts": 1538808000,
            "count": 0
        },
        {
            "ts": 1538809200,
            "count": 0
        },
        {
            "ts": 1538810400,
            "count": 0
        },
        {
            "ts": 1538811600,
            "count": 0
        },
        {
            "ts": 1538812800,
            "count": 0
        },
        {
            "ts": 1538814000,
            "count": 0
        },
        {
            "ts": 1538815200,
            "count": 0
        },
        {
            "ts": 1538816400,
            "count": 0
        },
        {
            "ts": 1538817600,
            "count": 0
        },
        {
            "ts": 1538818800,
            "count": 0
        },
        {
            "ts": 1538820000,
            "count": 0
        },
        {
            "ts": 1538821200,
            "count": 0
        },
        {
            "ts": 1538822400,
            "count": 0
        },
        {
            "ts": 1538823600,
            "count": 0
        },
        {
            "ts": 1538824800,
            "count": 0
        },
        {
            "ts": 1538826000,
            "count": 0
        },
        {
            "ts": 1538827200,
            "count": 0
        },
        {
            "ts": 1538828400,
            "count": 0
        },
        {
            "ts": 1538829600,
            "count": 0
        },
        {
            "ts": 1538830800,
            "count": 0
        },
        {
            "ts": 1538832000,
            "count": 0
        },
        {
            "ts": 1538833200,
            "count": 0
        },
        {
            "ts": 1538834400,
            "count": 0
        },
        {
            "ts": 1538835600,
            "count": 0
        },
        {
            "ts": 1538836800,
            "count": 0
        },
        {
            "ts": 1538838000,
            "count": 0
        },
        {
            "ts": 1538839200,
            "count": 0
        },
        {
            "ts": 1538840400,
            "count": 0
        },
        {
            "ts": 1538841600,
            "count": 0
        },
        {
            "ts": 1538842800,
            "count": 0
        },
        {
            "ts": 1538844000,
            "count": 0
        },
        {
            "ts": 1538845200,
            "count": 0
        },
        {
            "ts": 1538846400,
            "count": 0
        },
        {
            "ts": 1538847600,
            "count": 0
        },
        {
            "ts": 1538848800,
            "count": 0
        },
        {
            "ts": 1538850000,
            "count": 0
        },
        {
            "ts": 1538851200,
            "count": 0
        },
        {
            "ts": 1538852400,
            "count": 1
        },
        {
            "ts": 1538853600,
            "count": 0
        },
        {
            "ts": 1538854800,
            "count": 0
        },
        {
            "ts": 1538856000,
            "count": 0
        },
        {
            "ts": 1538857200,
            "count": 0
        },
        {
            "ts": 1538858400,
            "count": 0
        },
        {
            "ts": 1538859600,
            "count": 0
        },
        {
            "ts": 1538860800,
            "count": 0
        },
        {
            "ts": 1538862000,
            "count": 0
        },
        {
            "ts": 1538863200,
            "count": 0
        },
        {
            "ts": 1538864400,
            "count": 0
        },
        {
            "ts": 1538865600,
            "count": 0
        },
        {
            "ts": 1538866800,
            "count": 0
        },
        {
            "ts": 1538868000,
            "count": 0
        },
        {
            "ts": 1538869200,
            "count": 0
        },
        {
            "ts": 1538870400,
            "count": 0
        },
        {
            "ts": 1538871600,
            "count": 0
        },
        {
            "ts": 1538872800,
            "count": 0
        },
        {
            "ts": 1538874000,
            "count": 0
        },
        {
            "ts": 1538875200,
            "count": 0
        },
        {
            "ts": 1538876400,
            "count": 0
        },
        {
            "ts": 1538877600,
            "count": 0
        },
        {
            "ts": 1538878800,
            "count": 0
        },
        {
            "ts": 1538880000,
            "count": 0
        },
        {
            "ts": 1538881200,
            "count": 0
        },
        {
            "ts": 1538882400,
            "count": 0
        },
        {
            "ts": 1538883600,
            "count": 0
        }
    ],
    "meta": {}
}