{
    "data": [
        {
            "ts": 1547784000,
            "count": 0
        },
        {
            "ts": 1547785200,
            "count": 0
        },
        {
            "ts": 1547786400,
            "count": 0
        },
        {
            "ts": 1547787600,
            "count": 0
        },
        {
            "ts": 1547788800,
            "count": 0
        },
        {
            "ts": 1547790000,
            "count": 0
        },
        {
            "ts": 1547791200,
            "count": 0
        },
        {
            "ts": 1547792400,
            "count": 0
        },
        {
            "ts": 1547793600,
            "count": 0
        },
        {
            "ts": 1547794800,
            "count": 0
        },
        {
            "ts": 1547796000,
            "count": 1
        },
        {
            "ts": 1547797200,
            "count": 0
        },
        {
            "ts": 1547798400,
            "count": 0
        },
        {
            "ts": 1547799600,
            "count": 0
        },
        {
            "ts": 1547800800,
            "count": 0
        },
        {
            "ts": 1547802000,
            "count": 0
        },
        {
            "ts": 1547803200,
            "count": 0
        },
        {
            "ts": 1547804400,
            "count": 0
        },
        {
            "ts": 1547805600,
            "count": 0
        },
        {
            "ts": 1547806800,
            "count": 0
        },
        {
            "ts": 1547808000,
            "count": 0
        },
        {
            "ts": 1547809200,
            "count": 0
        },
        {
            "ts": 1547810400,
            "count": 0
        },
        {
            "ts": 1547811600,
            "count": 0
        },
        {
            "ts": 1547812800,
            "count": 0
        },
        {
            "ts": 1547814000,
            "count": 0
        },
        {
            "ts": 1547815200,
            "count": 0
        },
        {
            "ts": 1547816400,
            "count": 0
        },
        {
            "ts": 1547817600,
            "count": 0
        },
        {
            "ts": 1547818800,
            "count": 0
        },
        {
            "ts": 1547820000,
            "count": 0
        },
        {
            "ts": 1547821200,
            "count": 0
        },
        {
            "ts": 1547822400,
            "count": 0
        },
        {
            "ts": 1547823600,
            "count": 1
        },
        {
            "ts": 1547824800,
            "count": 0
        },
        {
            "ts": 1547826000,
            "count": 0
        },
        {
            "ts": 1547827200,
            "count": 0
        },
        {
            "ts": 1547828400,
            "count": 0
        },
        {
            "ts": 1547829600,
            "count": 0
        },
        {
            "ts": 1547830800,
            "count": 0
        },
        {
            "ts": 1547832000,
            "count": 0
        },
        {
            "ts": 1547833200,
            "count": 0
        },
        {
            "ts": 1547834400,
            "count": 0
        },
        {
            "ts": 1547835600,
            "count": 0
        },
        {
            "ts": 1547836800,
            "count": 0
        },
        {
            "ts": 1547838000,
            "count": 0
        },
        {
            "ts": 1547839200,
            "count": 0
        },
        {
            "ts": 1547840400,
            "count": 0
        },
        {
            "ts": 1547841600,
            "count": 0
        },
        {
            "ts": 1547842800,
            "count": 0
        },
        {
            "ts": 1547844000,
            "count": 0
        },
        {
            "ts": 1547845200,
            "count": 0
        },
        {
            "ts": 1547846400,
            "count": 0
        },
        {
            "ts": 1547847600,
            "count": 0
        },
        {
            "ts": 1547848800,
            "count": 0
        },
        {
            "ts": 1547850000,
            "count": 0
        },
        {
            "ts": 1547851200,
            "count": 0
        },
        {
            "ts": 1547852400,
            "count": 0
        },
        {
            "ts": 1547853600,
            "count": 0
        },
        {
            "ts": 1547854800,
            "count": 0
        },
        {
            "ts": 1547856000,
            "count": 0
        },
        {
            "ts": 1547857200,
            "count": 1
        },
        {
            "ts": 1547858400,
            "count": 0
        },
        {
            "ts": 1547859600,
            "count": 0
        },
        {
            "ts": 1547860800,
            "count": 0
        },
        {
            "ts": 1547862000,
            "count": 0
        },
        {
            "ts": 1547863200,
            "count": 0
        },
        {
            "ts": 1547864400,
            "count": 0
        },
        {
            "ts": 1547865600,
            "count": 0
        },
        {
            "ts": 1547866800,
            "count": 0
        },
        {
            "ts": 1547868000,
            "count": 0
        },
        {
            "ts": 1547869200,
            "count": 0
        }
    ],
    "meta": {}
}