{
    "data": [
        {
            "ts": 1599451200,
            "count": 0
        },
        {
            "ts": 1599452400,
            "count": 0
        },
        {
            "ts": 1599453600,
            "count": 0
        },
        {
            "ts": 1599454800,
            "count": 0
        },
        {
            "ts": 1599456000,
            "count": 0
        },
        {
            "ts": 1599457200,
            "count": 0
        },
        {
            "ts": 1599458400,
            "count": 0
        },
        {
            "ts": 1599459600,
            "count": 0
        },
        {
            "ts": 1599460800,
            "count": 0
        },
        {
            "ts": 1599462000,
            "count": 0
        },
        {
            "ts": 1599463200,
            "count": 0
        },
        {
            "ts": 1599464400,
            "count": 0
        },
        {
            "ts": 1599465600,
            "count": 0
        },
        {
            "ts": 1599466800,
            "count": 0
        },
        {
            "ts": 1599468000,
            "count": 0
        },
        {
            "ts": 1599469200,
            "count": 0
        },
        {
            "ts": 1599470400,
            "count": 0
        },
        {
            "ts": 1599471600,
            "count": 0
        },
        {
            "ts": 1599472800,
            "count": 0
        },
        {
            "ts": 1599474000,
            "count": 0
        },
        {
            "ts": 1599475200,
            "count": 0
        },
        {
            "ts": 1599476400,
            "count": 0
        },
        {
            "ts": 1599477600,
            "count": 0
        },
        {
            "ts": 1599478800,
            "count": 0
        },
        {
            "ts": 1599480000,
            "count": 0
        },
        {
            "ts": 1599481200,
            "count": 0
        },
        {
            "ts": 1599482400,
            "count": 0
        },
        {
            "ts": 1599483600,
            "count": 0
        },
        {
            "ts": 1599484800,
            "count": 0
        },
        {
            "ts": 1599486000,
            "count": 0
        },
        {
            "ts": 1599487200,
            "count": 0
        },
        {
            "ts": 1599488400,
            "count": 0
        },
        {
            "ts": 1599489600,
            "count": 0
        },
        {
            "ts": 1599490800,
            "count": 0
        },
        {
            "ts": 1599492000,
            "count": 0
        },
        {
            "ts": 1599493200,
            "count": 0
        },
        {
            "ts": 1599494400,
            "count": 0
        },
        {
            "ts": 1599495600,
            "count": 0
        },
        {
            "ts": 1599496800,
            "count": 0
        },
        {
            "ts": 1599498000,
            "count": 0
        },
        {
            "ts": 1599499200,
            "count": 0
        },
        {
            "ts": 1599500400,
            "count": 0
        },
        {
            "ts": 1599501600,
            "count": 0
        },
        {
            "ts": 1599502800,
            "count": 0
        },
        {
            "ts": 1599504000,
            "count": 0
        },
        {
            "ts": 1599505200,
            "count": 0
        },
        {
            "ts": 1599506400,
            "count": 0
        },
        {
            "ts": 1599507600,
            "count": 0
        },
        {
            "ts": 1599508800,
            "count": 0
        },
        {
            "ts": 1599510000,
            "count": 0
        },
        {
            "ts": 1599511200,
            "count": 0
        },
        {
            "ts": 1599512400,
            "count": 0
        },
        {
            "ts": 1599513600,
            "count": 0
        },
        {
            "ts": 1599514800,
            "count": 0
        },
        {
            "ts": 1599516000,
            "count": 0
        },
        {
            "ts": 1599517200,
            "count": 0
        },
        {
            "ts": 1599518400,
            "count": 0
        },
        {
            "ts": 1599519600,
            "count": 0
        },
        {
            "ts": 1599520800,
            "count": 0
        },
        {
            "ts": 1599522000,
            "count": 0
        },
        {
            "ts": 1599523200,
            "count": 0
        },
        {
            "ts": 1599524400,
            "count": 0
        },
        {
            "ts": 1599525600,
            "count": 0
        },
        {
            "ts": 1599526800,
            "count": 0
        },
        {
            "ts": 1599528000,
            "count": 0
        },
        {
            "ts": 1599529200,
            "count": 0
        },
        {
            "ts": 1599530400,
            "count": 0
        },
        {
            "ts": 1599531600,
            "count": 0
        },
        {
            "ts": 1599532800,
            "count": 0
        },
        {
            "ts": 1599534000,
            "count": 0
        },
        {
            "ts": 1599535200,
            "count": 0
        },
        {
            "ts": 1599536400,
            "count": 0
        }
    ],
    "meta": {}
}