{
    "data": [
        {
            "ts": 1592539200,
            "count": 0
        },
        {
            "ts": 1592540400,
            "count": 0
        },
        {
            "ts": 1592541600,
            "count": 0
        },
        {
            "ts": 1592542800,
            "count": 0
        },
        {
            "ts": 1592544000,
            "count": 0
        },
        {
            "ts": 1592545200,
            "count": 0
        },
        {
            "ts": 1592546400,
            "count": 0
        },
        {
            "ts": 1592547600,
            "count": 0
        },
        {
            "ts": 1592548800,
            "count": 0
        },
        {
            "ts": 1592550000,
            "count": 0
        },
        {
            "ts": 1592551200,
            "count": 0
        },
        {
            "ts": 1592552400,
            "count": 0
        },
        {
            "ts": 1592553600,
            "count": 0
        },
        {
            "ts": 1592554800,
            "count": 0
        },
        {
            "ts": 1592556000,
            "count": 0
        },
        {
            "ts": 1592557200,
            "count": 0
        },
        {
            "ts": 1592558400,
            "count": 0
        },
        {
            "ts": 1592559600,
            "count": 0
        },
        {
            "ts": 1592560800,
            "count": 0
        },
        {
            "ts": 1592562000,
            "count": 0
        },
        {
            "ts": 1592563200,
            "count": 0
        },
        {
            "ts": 1592564400,
            "count": 0
        },
        {
            "ts": 1592565600,
            "count": 0
        },
        {
            "ts": 1592566800,
            "count": 0
        },
        {
            "ts": 1592568000,
            "count": 0
        },
        {
            "ts": 1592569200,
            "count": 0
        },
        {
            "ts": 1592570400,
            "count": 0
        },
        {
            "ts": 1592571600,
            "count": 0
        },
        {
            "ts": 1592572800,
            "count": 0
        },
        {
            "ts": 1592574000,
            "count": 0
        },
        {
            "ts": 1592575200,
            "count": 0
        },
        {
            "ts": 1592576400,
            "count": 0
        },
        {
            "ts": 1592577600,
            "count": 0
        },
        {
            "ts": 1592578800,
            "count": 0
        },
        {
            "ts": 1592580000,
            "count": 0
        },
        {
            "ts": 1592581200,
            "count": 0
        },
        {
            "ts": 1592582400,
            "count": 0
        },
        {
            "ts": 1592583600,
            "count": 0
        },
        {
            "ts": 1592584800,
            "count": 0
        },
        {
            "ts": 1592586000,
            "count": 0
        },
        {
            "ts": 1592587200,
            "count": 0
        },
        {
            "ts": 1592588400,
            "count": 0
        },
        {
            "ts": 1592589600,
            "count": 0
        },
        {
            "ts": 1592590800,
            "count": 0
        },
        {
            "ts": 1592592000,
            "count": 0
        },
        {
            "ts": 1592593200,
            "count": 0
        },
        {
            "ts": 1592594400,
            "count": 0
        },
        {
            "ts": 1592595600,
            "count": 0
        },
        {
            "ts": 1592596800,
            "count": 0
        },
        {
            "ts": 1592598000,
            "count": 0
        },
        {
            "ts": 1592599200,
            "count": 0
        },
        {
            "ts": 1592600400,
            "count": 0
        },
        {
            "ts": 1592601600,
            "count": 0
        },
        {
            "ts": 1592602800,
            "count": 0
        },
        {
            "ts": 1592604000,
            "count": 0
        },
        {
            "ts": 1592605200,
            "count": 0
        },
        {
            "ts": 1592606400,
            "count": 0
        },
        {
            "ts": 1592607600,
            "count": 0
        },
        {
            "ts": 1592608800,
            "count": 0
        },
        {
            "ts": 1592610000,
            "count": 0
        },
        {
            "ts": 1592611200,
            "count": 0
        },
        {
            "ts": 1592612400,
            "count": 0
        },
        {
            "ts": 1592613600,
            "count": 0
        },
        {
            "ts": 1592614800,
            "count": 0
        },
        {
            "ts": 1592616000,
            "count": 0
        },
        {
            "ts": 1592617200,
            "count": 0
        },
        {
            "ts": 1592618400,
            "count": 0
        },
        {
            "ts": 1592619600,
            "count": 0
        },
        {
            "ts": 1592620800,
            "count": 0
        },
        {
            "ts": 1592622000,
            "count": 0
        },
        {
            "ts": 1592623200,
            "count": 0
        },
        {
            "ts": 1592624400,
            "count": 0
        }
    ],
    "meta": {}
}