{
    "data": [
        {
            "ts": 1584676800,
            "count": 0
        },
        {
            "ts": 1584678000,
            "count": 0
        },
        {
            "ts": 1584679200,
            "count": 0
        },
        {
            "ts": 1584680400,
            "count": 0
        },
        {
            "ts": 1584681600,
            "count": 0
        },
        {
            "ts": 1584682800,
            "count": 0
        },
        {
            "ts": 1584684000,
            "count": 0
        },
        {
            "ts": 1584685200,
            "count": 0
        },
        {
            "ts": 1584686400,
            "count": 0
        },
        {
            "ts": 1584687600,
            "count": 0
        },
        {
            "ts": 1584688800,
            "count": 0
        },
        {
            "ts": 1584690000,
            "count": 1
        },
        {
            "ts": 1584691200,
            "count": 0
        },
        {
            "ts": 1584692400,
            "count": 0
        },
        {
            "ts": 1584693600,
            "count": 0
        },
        {
            "ts": 1584694800,
            "count": 0
        },
        {
            "ts": 1584696000,
            "count": 0
        },
        {
            "ts": 1584697200,
            "count": 0
        },
        {
            "ts": 1584698400,
            "count": 0
        },
        {
            "ts": 1584699600,
            "count": 0
        },
        {
            "ts": 1584700800,
            "count": 0
        },
        {
            "ts": 1584702000,
            "count": 0
        },
        {
            "ts": 1584703200,
            "count": 0
        },
        {
            "ts": 1584704400,
            "count": 0
        },
        {
            "ts": 1584705600,
            "count": 0
        },
        {
            "ts": 1584706800,
            "count": 0
        },
        {
            "ts": 1584708000,
            "count": 0
        },
        {
            "ts": 1584709200,
            "count": 0
        },
        {
            "ts": 1584710400,
            "count": 0
        },
        {
            "ts": 1584711600,
            "count": 0
        },
        {
            "ts": 1584712800,
            "count": 0
        },
        {
            "ts": 1584714000,
            "count": 0
        },
        {
            "ts": 1584715200,
            "count": 0
        },
        {
            "ts": 1584716400,
            "count": 0
        },
        {
            "ts": 1584717600,
            "count": 0
        },
        {
            "ts": 1584718800,
            "count": 0
        },
        {
            "ts": 1584720000,
            "count": 0
        },
        {
            "ts": 1584721200,
            "count": 0
        },
        {
            "ts": 1584722400,
            "count": 0
        },
        {
            "ts": 1584723600,
            "count": 0
        },
        {
            "ts": 1584724800,
            "count": 0
        },
        {
            "ts": 1584726000,
            "count": 0
        },
        {
            "ts": 1584727200,
            "count": 0
        },
        {
            "ts": 1584728400,
            "count": 0
        },
        {
            "ts": 1584729600,
            "count": 0
        },
        {
            "ts": 1584730800,
            "count": 0
        },
        {
            "ts": 1584732000,
            "count": 0
        },
        {
            "ts": 1584733200,
            "count": 0
        },
        {
            "ts": 1584734400,
            "count": 0
        },
        {
            "ts": 1584735600,
            "count": 0
        },
        {
            "ts": 1584736800,
            "count": 0
        },
        {
            "ts": 1584738000,
            "count": 0
        },
        {
            "ts": 1584739200,
            "count": 0
        },
        {
            "ts": 1584740400,
            "count": 0
        },
        {
            "ts": 1584741600,
            "count": 0
        },
        {
            "ts": 1584742800,
            "count": 0
        },
        {
            "ts": 1584744000,
            "count": 0
        },
        {
            "ts": 1584745200,
            "count": 0
        },
        {
            "ts": 1584746400,
            "count": 0
        },
        {
            "ts": 1584747600,
            "count": 0
        },
        {
            "ts": 1584748800,
            "count": 0
        },
        {
            "ts": 1584750000,
            "count": 0
        },
        {
            "ts": 1584751200,
            "count": 0
        },
        {
            "ts": 1584752400,
            "count": 0
        },
        {
            "ts": 1584753600,
            "count": 0
        },
        {
            "ts": 1584754800,
            "count": 0
        },
        {
            "ts": 1584756000,
            "count": 0
        },
        {
            "ts": 1584757200,
            "count": 0
        },
        {
            "ts": 1584758400,
            "count": 0
        },
        {
            "ts": 1584759600,
            "count": 0
        },
        {
            "ts": 1584760800,
            "count": 0
        },
        {
            "ts": 1584762000,
            "count": 0
        }
    ],
    "meta": {}
}