{
    "data": [
        {
            "ts": 1542690000,
            "count": 0
        },
        {
            "ts": 1542691200,
            "count": 0
        },
        {
            "ts": 1542692400,
            "count": 0
        },
        {
            "ts": 1542693600,
            "count": 0
        },
        {
            "ts": 1542694800,
            "count": 0
        },
        {
            "ts": 1542696000,
            "count": 0
        },
        {
            "ts": 1542697200,
            "count": 0
        },
        {
            "ts": 1542698400,
            "count": 0
        },
        {
            "ts": 1542699600,
            "count": 0
        },
        {
            "ts": 1542700800,
            "count": 0
        },
        {
            "ts": 1542702000,
            "count": 0
        },
        {
            "ts": 1542703200,
            "count": 0
        },
        {
            "ts": 1542704400,
            "count": 0
        },
        {
            "ts": 1542705600,
            "count": 0
        },
        {
            "ts": 1542706800,
            "count": 1
        },
        {
            "ts": 1542708000,
            "count": 0
        },
        {
            "ts": 1542709200,
            "count": 0
        },
        {
            "ts": 1542710400,
            "count": 0
        },
        {
            "ts": 1542711600,
            "count": 1
        },
        {
            "ts": 1542712800,
            "count": 0
        },
        {
            "ts": 1542714000,
            "count": 0
        },
        {
            "ts": 1542715200,
            "count": 0
        },
        {
            "ts": 1542716400,
            "count": 0
        },
        {
            "ts": 1542717600,
            "count": 0
        },
        {
            "ts": 1542718800,
            "count": 0
        },
        {
            "ts": 1542720000,
            "count": 0
        },
        {
            "ts": 1542721200,
            "count": 0
        },
        {
            "ts": 1542722400,
            "count": 0
        },
        {
            "ts": 1542723600,
            "count": 0
        },
        {
            "ts": 1542724800,
            "count": 0
        },
        {
            "ts": 1542726000,
            "count": 0
        },
        {
            "ts": 1542727200,
            "count": 0
        },
        {
            "ts": 1542728400,
            "count": 0
        },
        {
            "ts": 1542729600,
            "count": 0
        },
        {
            "ts": 1542730800,
            "count": 0
        },
        {
            "ts": 1542732000,
            "count": 0
        },
        {
            "ts": 1542733200,
            "count": 0
        },
        {
            "ts": 1542734400,
            "count": 0
        },
        {
            "ts": 1542735600,
            "count": 0
        },
        {
            "ts": 1542736800,
            "count": 0
        },
        {
            "ts": 1542738000,
            "count": 1
        },
        {
            "ts": 1542739200,
            "count": 0
        },
        {
            "ts": 1542740400,
            "count": 0
        },
        {
            "ts": 1542741600,
            "count": 0
        },
        {
            "ts": 1542742800,
            "count": 0
        },
        {
            "ts": 1542744000,
            "count": 0
        },
        {
            "ts": 1542745200,
            "count": 0
        },
        {
            "ts": 1542746400,
            "count": 0
        },
        {
            "ts": 1542747600,
            "count": 0
        },
        {
            "ts": 1542748800,
            "count": 0
        },
        {
            "ts": 1542750000,
            "count": 0
        },
        {
            "ts": 1542751200,
            "count": 0
        },
        {
            "ts": 1542752400,
            "count": 0
        },
        {
            "ts": 1542753600,
            "count": 0
        },
        {
            "ts": 1542754800,
            "count": 0
        },
        {
            "ts": 1542756000,
            "count": 0
        },
        {
            "ts": 1542757200,
            "count": 1
        },
        {
            "ts": 1542758400,
            "count": 1
        },
        {
            "ts": 1542759600,
            "count": 0
        },
        {
            "ts": 1542760800,
            "count": 0
        },
        {
            "ts": 1542762000,
            "count": 0
        },
        {
            "ts": 1542763200,
            "count": 0
        },
        {
            "ts": 1542764400,
            "count": 0
        },
        {
            "ts": 1542765600,
            "count": 0
        },
        {
            "ts": 1542766800,
            "count": 0
        },
        {
            "ts": 1542768000,
            "count": 0
        },
        {
            "ts": 1542769200,
            "count": 0
        },
        {
            "ts": 1542770400,
            "count": 0
        },
        {
            "ts": 1542771600,
            "count": 0
        },
        {
            "ts": 1542772800,
            "count": 0
        },
        {
            "ts": 1542774000,
            "count": 0
        },
        {
            "ts": 1542775200,
            "count": 0
        }
    ],
    "meta": {}
}