{
    "data": [
        {
            "ts": 1518670800,
            "count": 0
        },
        {
            "ts": 1518672000,
            "count": 0
        },
        {
            "ts": 1518673200,
            "count": 0
        },
        {
            "ts": 1518674400,
            "count": 0
        },
        {
            "ts": 1518675600,
            "count": 0
        },
        {
            "ts": 1518676800,
            "count": 0
        },
        {
            "ts": 1518678000,
            "count": 0
        },
        {
            "ts": 1518679200,
            "count": 0
        },
        {
            "ts": 1518680400,
            "count": 0
        },
        {
            "ts": 1518681600,
            "count": 0
        },
        {
            "ts": 1518682800,
            "count": 0
        },
        {
            "ts": 1518684000,
            "count": 0
        },
        {
            "ts": 1518685200,
            "count": 0
        },
        {
            "ts": 1518686400,
            "count": 0
        },
        {
            "ts": 1518687600,
            "count": 0
        },
        {
            "ts": 1518688800,
            "count": 0
        },
        {
            "ts": 1518690000,
            "count": 0
        },
        {
            "ts": 1518691200,
            "count": 0
        },
        {
            "ts": 1518692400,
            "count": 0
        },
        {
            "ts": 1518693600,
            "count": 0
        },
        {
            "ts": 1518694800,
            "count": 0
        },
        {
            "ts": 1518696000,
            "count": 0
        },
        {
            "ts": 1518697200,
            "count": 0
        },
        {
            "ts": 1518698400,
            "count": 0
        },
        {
            "ts": 1518699600,
            "count": 0
        },
        {
            "ts": 1518700800,
            "count": 0
        },
        {
            "ts": 1518702000,
            "count": 0
        },
        {
            "ts": 1518703200,
            "count": 0
        },
        {
            "ts": 1518704400,
            "count": 0
        },
        {
            "ts": 1518705600,
            "count": 0
        },
        {
            "ts": 1518706800,
            "count": 0
        },
        {
            "ts": 1518708000,
            "count": 0
        },
        {
            "ts": 1518709200,
            "count": 0
        },
        {
            "ts": 1518710400,
            "count": 0
        },
        {
            "ts": 1518711600,
            "count": 0
        },
        {
            "ts": 1518712800,
            "count": 0
        },
        {
            "ts": 1518714000,
            "count": 0
        },
        {
            "ts": 1518715200,
            "count": 0
        },
        {
            "ts": 1518716400,
            "count": 0
        },
        {
            "ts": 1518717600,
            "count": 0
        },
        {
            "ts": 1518718800,
            "count": 0
        },
        {
            "ts": 1518720000,
            "count": 0
        },
        {
            "ts": 1518721200,
            "count": 0
        },
        {
            "ts": 1518722400,
            "count": 0
        },
        {
            "ts": 1518723600,
            "count": 0
        },
        {
            "ts": 1518724800,
            "count": 0
        },
        {
            "ts": 1518726000,
            "count": 0
        },
        {
            "ts": 1518727200,
            "count": 0
        },
        {
            "ts": 1518728400,
            "count": 0
        },
        {
            "ts": 1518729600,
            "count": 0
        },
        {
            "ts": 1518730800,
            "count": 0
        },
        {
            "ts": 1518732000,
            "count": 0
        },
        {
            "ts": 1518733200,
            "count": 0
        },
        {
            "ts": 1518734400,
            "count": 0
        },
        {
            "ts": 1518735600,
            "count": 0
        },
        {
            "ts": 1518736800,
            "count": 0
        },
        {
            "ts": 1518738000,
            "count": 0
        },
        {
            "ts": 1518739200,
            "count": 0
        },
        {
            "ts": 1518740400,
            "count": 0
        },
        {
            "ts": 1518741600,
            "count": 0
        },
        {
            "ts": 1518742800,
            "count": 0
        },
        {
            "ts": 1518744000,
            "count": 0
        },
        {
            "ts": 1518745200,
            "count": 0
        },
        {
            "ts": 1518746400,
            "count": 0
        },
        {
            "ts": 1518747600,
            "count": 0
        },
        {
            "ts": 1518748800,
            "count": 0
        },
        {
            "ts": 1518750000,
            "count": 0
        },
        {
            "ts": 1518751200,
            "count": 0
        },
        {
            "ts": 1518752400,
            "count": 0
        },
        {
            "ts": 1518753600,
            "count": 0
        },
        {
            "ts": 1518754800,
            "count": 0
        },
        {
            "ts": 1518756000,
            "count": 0
        }
    ],
    "meta": {}
}