{
    "data": [
        {
            "ts": 1553749200,
            "count": 0
        },
        {
            "ts": 1553750400,
            "count": 0
        },
        {
            "ts": 1553751600,
            "count": 0
        },
        {
            "ts": 1553752800,
            "count": 0
        },
        {
            "ts": 1553754000,
            "count": 0
        },
        {
            "ts": 1553755200,
            "count": 2
        },
        {
            "ts": 1553756400,
            "count": 0
        },
        {
            "ts": 1553757600,
            "count": 0
        },
        {
            "ts": 1553758800,
            "count": 0
        },
        {
            "ts": 1553760000,
            "count": 0
        },
        {
            "ts": 1553761200,
            "count": 0
        },
        {
            "ts": 1553762400,
            "count": 0
        },
        {
            "ts": 1553763600,
            "count": 0
        },
        {
            "ts": 1553764800,
            "count": 0
        },
        {
            "ts": 1553766000,
            "count": 0
        },
        {
            "ts": 1553767200,
            "count": 0
        },
        {
            "ts": 1553768400,
            "count": 0
        },
        {
            "ts": 1553769600,
            "count": 0
        },
        {
            "ts": 1553770800,
            "count": 0
        },
        {
            "ts": 1553772000,
            "count": 0
        },
        {
            "ts": 1553773200,
            "count": 0
        },
        {
            "ts": 1553774400,
            "count": 0
        },
        {
            "ts": 1553775600,
            "count": 0
        },
        {
            "ts": 1553776800,
            "count": 0
        },
        {
            "ts": 1553778000,
            "count": 0
        },
        {
            "ts": 1553779200,
            "count": 0
        },
        {
            "ts": 1553780400,
            "count": 0
        },
        {
            "ts": 1553781600,
            "count": 0
        },
        {
            "ts": 1553782800,
            "count": 0
        },
        {
            "ts": 1553784000,
            "count": 0
        },
        {
            "ts": 1553785200,
            "count": 0
        },
        {
            "ts": 1553786400,
            "count": 0
        },
        {
            "ts": 1553787600,
            "count": 0
        },
        {
            "ts": 1553788800,
            "count": 0
        },
        {
            "ts": 1553790000,
            "count": 0
        },
        {
            "ts": 1553791200,
            "count": 0
        },
        {
            "ts": 1553792400,
            "count": 0
        },
        {
            "ts": 1553793600,
            "count": 0
        },
        {
            "ts": 1553794800,
            "count": 0
        },
        {
            "ts": 1553796000,
            "count": 0
        },
        {
            "ts": 1553797200,
            "count": 0
        },
        {
            "ts": 1553798400,
            "count": 0
        },
        {
            "ts": 1553799600,
            "count": 0
        },
        {
            "ts": 1553800800,
            "count": 0
        },
        {
            "ts": 1553802000,
            "count": 0
        },
        {
            "ts": 1553803200,
            "count": 0
        },
        {
            "ts": 1553804400,
            "count": 0
        },
        {
            "ts": 1553805600,
            "count": 0
        },
        {
            "ts": 1553806800,
            "count": 0
        },
        {
            "ts": 1553808000,
            "count": 0
        },
        {
            "ts": 1553809200,
            "count": 0
        },
        {
            "ts": 1553810400,
            "count": 0
        },
        {
            "ts": 1553811600,
            "count": 0
        },
        {
            "ts": 1553812800,
            "count": 0
        },
        {
            "ts": 1553814000,
            "count": 0
        },
        {
            "ts": 1553815200,
            "count": 0
        },
        {
            "ts": 1553816400,
            "count": 0
        },
        {
            "ts": 1553817600,
            "count": 0
        },
        {
            "ts": 1553818800,
            "count": 0
        },
        {
            "ts": 1553820000,
            "count": 0
        },
        {
            "ts": 1553821200,
            "count": 0
        },
        {
            "ts": 1553822400,
            "count": 0
        },
        {
            "ts": 1553823600,
            "count": 0
        },
        {
            "ts": 1553824800,
            "count": 0
        },
        {
            "ts": 1553826000,
            "count": 0
        },
        {
            "ts": 1553827200,
            "count": 0
        },
        {
            "ts": 1553828400,
            "count": 0
        },
        {
            "ts": 1553829600,
            "count": 0
        },
        {
            "ts": 1553830800,
            "count": 0
        },
        {
            "ts": 1553832000,
            "count": 0
        },
        {
            "ts": 1553833200,
            "count": 0
        },
        {
            "ts": 1553834400,
            "count": 0
        }
    ],
    "meta": {}
}