{
    "data": [
        {
            "ts": 1569733200,
            "count": 0
        },
        {
            "ts": 1569734400,
            "count": 0
        },
        {
            "ts": 1569735600,
            "count": 0
        },
        {
            "ts": 1569736800,
            "count": 0
        },
        {
            "ts": 1569738000,
            "count": 0
        },
        {
            "ts": 1569739200,
            "count": 0
        },
        {
            "ts": 1569740400,
            "count": 0
        },
        {
            "ts": 1569741600,
            "count": 0
        },
        {
            "ts": 1569742800,
            "count": 0
        },
        {
            "ts": 1569744000,
            "count": 0
        },
        {
            "ts": 1569745200,
            "count": 0
        },
        {
            "ts": 1569746400,
            "count": 0
        },
        {
            "ts": 1569747600,
            "count": 0
        },
        {
            "ts": 1569748800,
            "count": 0
        },
        {
            "ts": 1569750000,
            "count": 0
        },
        {
            "ts": 1569751200,
            "count": 0
        },
        {
            "ts": 1569752400,
            "count": 0
        },
        {
            "ts": 1569753600,
            "count": 0
        },
        {
            "ts": 1569754800,
            "count": 0
        },
        {
            "ts": 1569756000,
            "count": 0
        },
        {
            "ts": 1569757200,
            "count": 0
        },
        {
            "ts": 1569758400,
            "count": 0
        },
        {
            "ts": 1569759600,
            "count": 0
        },
        {
            "ts": 1569760800,
            "count": 1
        },
        {
            "ts": 1569762000,
            "count": 0
        },
        {
            "ts": 1569763200,
            "count": 0
        },
        {
            "ts": 1569764400,
            "count": 0
        },
        {
            "ts": 1569765600,
            "count": 0
        },
        {
            "ts": 1569766800,
            "count": 0
        },
        {
            "ts": 1569768000,
            "count": 0
        },
        {
            "ts": 1569769200,
            "count": 0
        },
        {
            "ts": 1569770400,
            "count": 0
        },
        {
            "ts": 1569771600,
            "count": 0
        },
        {
            "ts": 1569772800,
            "count": 0
        },
        {
            "ts": 1569774000,
            "count": 0
        },
        {
            "ts": 1569775200,
            "count": 0
        },
        {
            "ts": 1569776400,
            "count": 0
        },
        {
            "ts": 1569777600,
            "count": 1
        },
        {
            "ts": 1569778800,
            "count": 1
        },
        {
            "ts": 1569780000,
            "count": 0
        },
        {
            "ts": 1569781200,
            "count": 0
        },
        {
            "ts": 1569782400,
            "count": 0
        },
        {
            "ts": 1569783600,
            "count": 0
        },
        {
            "ts": 1569784800,
            "count": 0
        },
        {
            "ts": 1569786000,
            "count": 0
        },
        {
            "ts": 1569787200,
            "count": 0
        },
        {
            "ts": 1569788400,
            "count": 0
        },
        {
            "ts": 1569789600,
            "count": 0
        },
        {
            "ts": 1569790800,
            "count": 0
        },
        {
            "ts": 1569792000,
            "count": 0
        },
        {
            "ts": 1569793200,
            "count": 0
        },
        {
            "ts": 1569794400,
            "count": 0
        },
        {
            "ts": 1569795600,
            "count": 0
        },
        {
            "ts": 1569796800,
            "count": 0
        },
        {
            "ts": 1569798000,
            "count": 0
        },
        {
            "ts": 1569799200,
            "count": 0
        },
        {
            "ts": 1569800400,
            "count": 0
        },
        {
            "ts": 1569801600,
            "count": 0
        },
        {
            "ts": 1569802800,
            "count": 1
        },
        {
            "ts": 1569804000,
            "count": 0
        },
        {
            "ts": 1569805200,
            "count": 1
        },
        {
            "ts": 1569806400,
            "count": 0
        },
        {
            "ts": 1569807600,
            "count": 0
        },
        {
            "ts": 1569808800,
            "count": 0
        },
        {
            "ts": 1569810000,
            "count": 0
        },
        {
            "ts": 1569811200,
            "count": 0
        },
        {
            "ts": 1569812400,
            "count": 0
        },
        {
            "ts": 1569813600,
            "count": 0
        },
        {
            "ts": 1569814800,
            "count": 0
        },
        {
            "ts": 1569816000,
            "count": 0
        },
        {
            "ts": 1569817200,
            "count": 0
        },
        {
            "ts": 1569818400,
            "count": 0
        }
    ],
    "meta": {}
}