{
    "data": [
        {
            "ts": 1606626000,
            "count": 0
        },
        {
            "ts": 1606627200,
            "count": 0
        },
        {
            "ts": 1606628400,
            "count": 0
        },
        {
            "ts": 1606629600,
            "count": 0
        },
        {
            "ts": 1606630800,
            "count": 0
        },
        {
            "ts": 1606632000,
            "count": 0
        },
        {
            "ts": 1606633200,
            "count": 0
        },
        {
            "ts": 1606634400,
            "count": 0
        },
        {
            "ts": 1606635600,
            "count": 0
        },
        {
            "ts": 1606636800,
            "count": 0
        },
        {
            "ts": 1606638000,
            "count": 0
        },
        {
            "ts": 1606639200,
            "count": 0
        },
        {
            "ts": 1606640400,
            "count": 0
        },
        {
            "ts": 1606641600,
            "count": 0
        },
        {
            "ts": 1606642800,
            "count": 0
        },
        {
            "ts": 1606644000,
            "count": 0
        },
        {
            "ts": 1606645200,
            "count": 0
        },
        {
            "ts": 1606646400,
            "count": 0
        },
        {
            "ts": 1606647600,
            "count": 0
        },
        {
            "ts": 1606648800,
            "count": 0
        },
        {
            "ts": 1606650000,
            "count": 0
        },
        {
            "ts": 1606651200,
            "count": 0
        },
        {
            "ts": 1606652400,
            "count": 0
        },
        {
            "ts": 1606653600,
            "count": 0
        },
        {
            "ts": 1606654800,
            "count": 0
        },
        {
            "ts": 1606656000,
            "count": 0
        },
        {
            "ts": 1606657200,
            "count": 0
        },
        {
            "ts": 1606658400,
            "count": 0
        },
        {
            "ts": 1606659600,
            "count": 0
        },
        {
            "ts": 1606660800,
            "count": 0
        },
        {
            "ts": 1606662000,
            "count": 0
        },
        {
            "ts": 1606663200,
            "count": 0
        },
        {
            "ts": 1606664400,
            "count": 0
        },
        {
            "ts": 1606665600,
            "count": 0
        },
        {
            "ts": 1606666800,
            "count": 0
        },
        {
            "ts": 1606668000,
            "count": 0
        },
        {
            "ts": 1606669200,
            "count": 0
        },
        {
            "ts": 1606670400,
            "count": 0
        },
        {
            "ts": 1606671600,
            "count": 0
        },
        {
            "ts": 1606672800,
            "count": 0
        },
        {
            "ts": 1606674000,
            "count": 0
        },
        {
            "ts": 1606675200,
            "count": 0
        },
        {
            "ts": 1606676400,
            "count": 0
        },
        {
            "ts": 1606677600,
            "count": 0
        },
        {
            "ts": 1606678800,
            "count": 0
        },
        {
            "ts": 1606680000,
            "count": 0
        },
        {
            "ts": 1606681200,
            "count": 0
        },
        {
            "ts": 1606682400,
            "count": 0
        },
        {
            "ts": 1606683600,
            "count": 0
        },
        {
            "ts": 1606684800,
            "count": 0
        },
        {
            "ts": 1606686000,
            "count": 0
        },
        {
            "ts": 1606687200,
            "count": 0
        },
        {
            "ts": 1606688400,
            "count": 0
        },
        {
            "ts": 1606689600,
            "count": 0
        },
        {
            "ts": 1606690800,
            "count": 0
        },
        {
            "ts": 1606692000,
            "count": 0
        },
        {
            "ts": 1606693200,
            "count": 0
        },
        {
            "ts": 1606694400,
            "count": 0
        },
        {
            "ts": 1606695600,
            "count": 0
        },
        {
            "ts": 1606696800,
            "count": 0
        },
        {
            "ts": 1606698000,
            "count": 0
        },
        {
            "ts": 1606699200,
            "count": 0
        },
        {
            "ts": 1606700400,
            "count": 0
        },
        {
            "ts": 1606701600,
            "count": 0
        },
        {
            "ts": 1606702800,
            "count": 0
        },
        {
            "ts": 1606704000,
            "count": 0
        },
        {
            "ts": 1606705200,
            "count": 0
        },
        {
            "ts": 1606706400,
            "count": 0
        },
        {
            "ts": 1606707600,
            "count": 0
        },
        {
            "ts": 1606708800,
            "count": 0
        },
        {
            "ts": 1606710000,
            "count": 0
        },
        {
            "ts": 1606711200,
            "count": 0
        }
    ],
    "meta": {}
}