{
    "data": [
        {
            "ts": 1603515600,
            "count": 0
        },
        {
            "ts": 1603516800,
            "count": 0
        },
        {
            "ts": 1603518000,
            "count": 0
        },
        {
            "ts": 1603519200,
            "count": 0
        },
        {
            "ts": 1603520400,
            "count": 0
        },
        {
            "ts": 1603521600,
            "count": 0
        },
        {
            "ts": 1603522800,
            "count": 0
        },
        {
            "ts": 1603524000,
            "count": 0
        },
        {
            "ts": 1603525200,
            "count": 0
        },
        {
            "ts": 1603526400,
            "count": 0
        },
        {
            "ts": 1603527600,
            "count": 0
        },
        {
            "ts": 1603528800,
            "count": 0
        },
        {
            "ts": 1603530000,
            "count": 0
        },
        {
            "ts": 1603531200,
            "count": 0
        },
        {
            "ts": 1603532400,
            "count": 0
        },
        {
            "ts": 1603533600,
            "count": 0
        },
        {
            "ts": 1603534800,
            "count": 0
        },
        {
            "ts": 1603536000,
            "count": 0
        },
        {
            "ts": 1603537200,
            "count": 0
        },
        {
            "ts": 1603538400,
            "count": 0
        },
        {
            "ts": 1603539600,
            "count": 0
        },
        {
            "ts": 1603540800,
            "count": 0
        },
        {
            "ts": 1603542000,
            "count": 0
        },
        {
            "ts": 1603543200,
            "count": 0
        },
        {
            "ts": 1603544400,
            "count": 0
        },
        {
            "ts": 1603545600,
            "count": 0
        },
        {
            "ts": 1603546800,
            "count": 0
        },
        {
            "ts": 1603548000,
            "count": 0
        },
        {
            "ts": 1603549200,
            "count": 0
        },
        {
            "ts": 1603550400,
            "count": 0
        },
        {
            "ts": 1603551600,
            "count": 0
        },
        {
            "ts": 1603552800,
            "count": 0
        },
        {
            "ts": 1603554000,
            "count": 0
        },
        {
            "ts": 1603555200,
            "count": 0
        },
        {
            "ts": 1603556400,
            "count": 0
        },
        {
            "ts": 1603557600,
            "count": 0
        },
        {
            "ts": 1603558800,
            "count": 0
        },
        {
            "ts": 1603560000,
            "count": 0
        },
        {
            "ts": 1603561200,
            "count": 0
        },
        {
            "ts": 1603562400,
            "count": 0
        },
        {
            "ts": 1603563600,
            "count": 0
        },
        {
            "ts": 1603564800,
            "count": 0
        },
        {
            "ts": 1603566000,
            "count": 0
        },
        {
            "ts": 1603567200,
            "count": 0
        },
        {
            "ts": 1603568400,
            "count": 0
        },
        {
            "ts": 1603569600,
            "count": 0
        },
        {
            "ts": 1603570800,
            "count": 0
        },
        {
            "ts": 1603572000,
            "count": 0
        },
        {
            "ts": 1603573200,
            "count": 0
        },
        {
            "ts": 1603574400,
            "count": 0
        },
        {
            "ts": 1603575600,
            "count": 0
        },
        {
            "ts": 1603576800,
            "count": 0
        },
        {
            "ts": 1603578000,
            "count": 0
        },
        {
            "ts": 1603579200,
            "count": 0
        },
        {
            "ts": 1603580400,
            "count": 0
        },
        {
            "ts": 1603581600,
            "count": 0
        },
        {
            "ts": 1603582800,
            "count": 0
        },
        {
            "ts": 1603584000,
            "count": 0
        },
        {
            "ts": 1603585200,
            "count": 0
        },
        {
            "ts": 1603586400,
            "count": 0
        },
        {
            "ts": 1603587600,
            "count": 0
        },
        {
            "ts": 1603588800,
            "count": 0
        },
        {
            "ts": 1603590000,
            "count": 0
        },
        {
            "ts": 1603591200,
            "count": 0
        },
        {
            "ts": 1603592400,
            "count": 0
        },
        {
            "ts": 1603593600,
            "count": 0
        },
        {
            "ts": 1603594800,
            "count": 0
        },
        {
            "ts": 1603596000,
            "count": 0
        },
        {
            "ts": 1603597200,
            "count": 0
        },
        {
            "ts": 1603598400,
            "count": 0
        },
        {
            "ts": 1603599600,
            "count": 0
        },
        {
            "ts": 1603600800,
            "count": 0
        }
    ],
    "meta": {}
}